CHANGELOG.md
LICENSE
MANIFEST.in
README.md
setup.cfg
setup.py
pip_services3_memcached/__init__.py
pip_services3_memcached.egg-info/PKG-INFO
pip_services3_memcached.egg-info/SOURCES.txt
pip_services3_memcached.egg-info/dependency_links.txt
pip_services3_memcached.egg-info/requires.txt
pip_services3_memcached.egg-info/top_level.txt
pip_services3_memcached.egg-info/zip-safe
pip_services3_memcached/build/DefaultMemcachedFactory.py
pip_services3_memcached/build/__init__.py
pip_services3_memcached/cache/MemcachedCache.py
pip_services3_memcached/cache/__init__.py
pip_services3_memcached/lock/MemcachedLock.py
pip_services3_memcached/lock/__init__.py
test/cache/__init__.py
test/cache/test_MemcachedCache.py
test/fixtures/CacheFixture.py
test/fixtures/LockFixture.py
test/fixtures/__init__.py
test/lock/__init__.py
test/lock/test_MemcachedLock.py